odoo/addons/web_advanced_search/README.rst
odoo/addons/web_advanced_search/__init__.py
odoo/addons/web_advanced_search/__manifest__.py
odoo/addons/web_advanced_search/i18n/da.po
odoo/addons/web_advanced_search/i18n/de.po
odoo/addons/web_advanced_search/i18n/es.po
odoo/addons/web_advanced_search/i18n/fr.po
odoo/addons/web_advanced_search/i18n/hr.po
odoo/addons/web_advanced_search/i18n/nl.po
odoo/addons/web_advanced_search/i18n/nl_NL.po
odoo/addons/web_advanced_search/i18n/pt_BR.po
odoo/addons/web_advanced_search/i18n/web_advanced_search.pot
odoo/addons/web_advanced_search/readme/CONTRIBUTORS.rst
odoo/addons/web_advanced_search/readme/DESCRIPTION.rst
odoo/addons/web_advanced_search/readme/HISTORY.rst
odoo/addons/web_advanced_search/readme/ROADMAP.rst
odoo/addons/web_advanced_search/readme/USAGE.rst
odoo/addons/web_advanced_search/static/description/icon.png
odoo/addons/web_advanced_search/static/description/index.html
odoo/addons/web_advanced_search/static/src/css/web_advanced_search.less
odoo/addons/web_advanced_search/static/src/js/human_domain.js
odoo/addons/web_advanced_search/static/src/js/web_advanced_search.js
odoo/addons/web_advanced_search/static/src/xml/web_advanced_search.xml
odoo/addons/web_advanced_search/views/templates.xml
odoo11_addon_web_advanced_search-11.0.1.0.2.99.dev7.dist-info/METADATA
odoo11_addon_web_advanced_search-11.0.1.0.2.99.dev7.dist-info/WHEEL
odoo11_addon_web_advanced_search-11.0.1.0.2.99.dev7.dist-info/top_level.txt
odoo11_addon_web_advanced_search-11.0.1.0.2.99.dev7.dist-info/RECORD
